topocurve/SpectralFiltering.py
topocurve/TopoCurve.py
topocurve/__init__.py
topocurve-0.1.3.dist-info/licenses/LICENSE
topocurve-0.1.3.dist-info/METADATA
topocurve-0.1.3.dist-info/WHEEL
topocurve-0.1.3.dist-info/top_level.txt
topocurve-0.1.3.dist-info/RECORD
