Metadata-Version: 2.4
Name: topocurve
Version: 0.1.3
Summary: A package for processing digital elevation models.
Home-page: https://github.com/tschermer02/topoCurve1
Author: Taylor Schermer, Joel Nash, Nate Klema
Author-email: tschermer@fortlewis.edu, jxnash@fortlewis.edu, ntklema@fortlewis.edu
Classifier: License :: OSI Approved :: MIT License
Classifier: Programming Language :: Python :: 3
Classifier: Programming Language :: Python :: 3.6
Classifier: Programming Language :: Python :: 3.7
Classifier: Programming Language :: Python :: 3.8
Classifier: Programming Language :: Python :: 3.9
Requires-Python: >=3.6
License-File: LICENSE
Requires-Dist: numpy<2
Requires-Dist: scipy
Requires-Dist: zarr<2.13
Requires-Dist: numcodecs>0.12
Requires-Dist: Pillow
Requires-Dist: photutils<2.0,>=1.8
Requires-Dist: tifffile<2024.8
Requires-Dist: geotiff
Requires-Dist: scikit-learn
Requires-Dist: rasterio
Requires-Dist: pyproj
Requires-Dist: matplotlib
Dynamic: author
Dynamic: author-email
Dynamic: classifier
Dynamic: description
Dynamic: description-content-type
Dynamic: home-page
Dynamic: license-file
Dynamic: requires-dist
Dynamic: requires-python
Dynamic: summary
